pyzpace/__init__.py
pyzpace-0.0.dist-info/DESCRIPTION.rst
pyzpace-0.0.dist-info/METADATA
pyzpace-0.0.dist-info/RECORD
pyzpace-0.0.dist-info/WHEEL
pyzpace-0.0.dist-info/metadata.json
pyzpace-0.0.dist-info/top_level.txt
