Metadata-Version: 2.0
Name: pyzpace
Version: 0.0
Summary: Zach Pace's astronomy-related python tools
Home-page: http://github.com/zpace/python-personal
Author: Zach Pace
Author-email: zpace@astro.wisc.edu
License: MIT
Platform: UNKNOWN
